buenbit/__init__.py
buenbit/api_authentication.py
buenbit/api_client.py
buenbit-0.0.1.dist-info/METADATA
buenbit-0.0.1.dist-info/WHEEL
buenbit-0.0.1.dist-info/top_level.txt
buenbit-0.0.1.dist-info/RECORD
