Metadata-Version: 2.1
Name: buenbit
Version: 0.0.1
Summary: Buenbit API client.
Home-page: UNKNOWN
License: UNKNOWN
Platform: UNKNOWN
Classifier: Programming Language :: Python :: 3
Requires-Python: >=3.6
Requires-Dist: requests-openapi (==0.9.5)
Requires-Dist: requests
